HISTORY.rst
LICENSE
MANIFEST.in
README.rst
requirements.txt
setup.cfg
setup.py
bastion_ssh/__init__.py
bastion_ssh/argparser.py
bastion_ssh/bastionssh.py
bastion_ssh/config.py
bastion_ssh/context.py
bastion_ssh/errors.py
bastion_ssh/log.py
bastion_ssh/utils.py
bastion_ssh.egg-info/PKG-INFO
bastion_ssh.egg-info/SOURCES.txt
bastion_ssh.egg-info/dependency_links.txt
bastion_ssh.egg-info/not-zip-safe
bastion_ssh.egg-info/requires.txt
bastion_ssh.egg-info/top_level.txt
bastion_ssh/plugins/__init__.py
bastion_ssh/plugins/audit/__init__.py
bastion_ssh/plugins/audit/main.py
bastion_ssh/plugins/audit/screen.py
bastion_ssh/plugins/audit/stream.py
bastion_ssh/plugins/ssh/__init__.py
bastion_ssh/plugins/ssh/main.py
bastion_ssh/plugins/ssh/ssh_filter.py
bastion_ssh/plugins/ssh/ssh_transport.py