Metadata-Version: 1.1
Name: bastion-ssh
Version: 0.0.3
Summary: bastion host for ssh.
Home-page: http://www.python.org
Author: wcc526
Author-email: 949409306@qq.com
License: Apache 2.0
Keywords: bastion,bastion host for ssh
Platform: UNKNOWN
Classifier: Development Status :: 5 - Production/Stable
Classifier: Intended Audience :: Developers
Classifier: Natural Language :: English
Classifier: License :: OSI Approved :: Apache Software License
Classifier: Programming Language :: Python :: 2.7
